my_platform_sdk_package/__init__.py
my_platform_sdk_package/http_client.py
my_platform_sdk_package/main.py
my_platform_sdk_package/services/__init__.py
my_platform_sdk_package/services/api_key_model_service.py
my_platform_sdk_package/services/api_key_model_verify_service.py
my_platform_sdk_package/services/api_key_model_versioning_service.py
my_platform_sdk_package/services/api_key_repository_service.py
my_platform_sdk_package/services/api_key_service.py
my_platform_sdk_package-0.2.0.dist-info/licenses/LICENSE
my_platform_sdk_package-0.2.0.dist-info/METADATA
my_platform_sdk_package-0.2.0.dist-info/WHEEL
my_platform_sdk_package-0.2.0.dist-info/top_level.txt
my_platform_sdk_package-0.2.0.dist-info/RECORD
