Metadata-Version: 2.4
Name: my_platform_sdk_package
Version: 0.2.0
Summary: A simple my_platform_sdk_package
Author-email: ThinhNguyen <thinh@example.com>
License: MIT
Project-URL: Homepage, https://github.com/thinhtruongnguyen/python-my-sdk
Requires-Python: >=3.7
License-File: LICENSE
Dynamic: license-file
